{
  "name": "kyogre repo",
  "identifier": "com.kyogre.workshop",
  "website": "https://kyogre.xyz",
  "iconURL": "https://raw.githubusercontent.com/zxxvyv/repository/refs/heads/main/kyogre.jpg",
  "apps": [
    {
      "name": "Soundcloud ++",
      "subtitle": "Soundcloud with additional tweaks",
      "tintColor": "#E36678",
      "versions": [
        {
          "version": "8.22.2",
          "minOSVersion": "16.0",
          "downloadURL": "https://github.com/zxxvyv/repository/releases/download/IPA/SoundCloud_8.22.2_1754060114.ipa",
          "localizedDescription": "Soundcloud ++"
        }
      ],
      "version": "8.22.2"
    },
    {
      "name": "Duolingo ++",
      "subtitle": "Duolingo with additional tweaks",
      "tintColor": "#E36678",
      "versions": [
        {
          "version": "7.15.0",
          "minOSVersion": "16.0",
          "downloadURL": "https://github.com/zxxvyv/repository/releases/download/IPA/Deezer.v7.15.0.+.Deezelife.v0.5.ipa",
          "localizedDescription": "Duolingo ++"
        }
      ],
      "version": "7.15.0"
    }
  ],
  "news": [
    {
      "title": "All my apps in one place",
      "identifier": "zxxvyv",
      "caption": "Welcome to the official Feather repository of kyogres Workshop!\n\nHere, you can explore and download all of my free tweaked apps.",
      "tintColor": "E36678",
      "imageURL": "https://raw.githubusercontent.com/zxxvyv/repository/refs/heads/main/kyogre.jpg",
      "url": "https://kyogre.xyz",
      "date": "2025-02-03",
      "notify": true
    }
  ]
}
